ddt_request_history/__init__.py
ddt_request_history/panels/__init__.py
ddt_request_history/panels/request_history.html
ddt_request_history/panels/request_history.py
django_debug_toolbar_request_history-0.1.2.dist-info/DESCRIPTION.rst
django_debug_toolbar_request_history-0.1.2.dist-info/METADATA
django_debug_toolbar_request_history-0.1.2.dist-info/RECORD
django_debug_toolbar_request_history-0.1.2.dist-info/WHEEL
django_debug_toolbar_request_history-0.1.2.dist-info/metadata.json
django_debug_toolbar_request_history-0.1.2.dist-info/top_level.txt
